{
    "custom_fonts": ["https://fonts.googleapis.com/css2?family=Lato:ital,wght@0,100;0,300;0,400;0,700;0,900;1,100;1,300;1,400;1,700;1,900&family=Playfair+Display:ital,wght@0,400..900;1,400..900&family=Roboto:ital,wght@0,100..900;1,100..900&display=swap"],
    "variables": {
        "light": {
            "--font-sans": "'Roboto', sans-serif",
            "--font-mono": "source-code-pro, Menlo, Monaco, Consolas, 'Courier New', monospace",
            "--background": "60 56% 91%",
            "--foreground": "240 100% 25%",
            "--card": "60 56% 95%",
            "--card-foreground": "240 100% 25%",
            "--popover": "60 56% 95%",
            "--popover-foreground": "240 100% 25%",
            "--primary": "240 100% 25%",
            "--primary-foreground": "60 56% 91%",
            "--secondary": "60 30% 85%",
            "--secondary-foreground": "240 100% 25%",
            "--muted": "60 56% 91%",
            "--muted-foreground": "240 50% 35%",
            "--accent": "60 40% 85%",
            "--accent-foreground": "240 100% 25%",
            "--destructive": "0 84.2% 60.2%",
            "--destructive-foreground": "0 0% 100%",
            "--border": "240 50% 80%",
            "--input": "240 50% 80%",
            "--ring": "240 100% 25%",
            "--radius": "0.75rem",
            "--sidebar-background": "60 50% 88%",
            "--sidebar-foreground": "240 100% 25%",
            "--sidebar-primary": "240 100% 25%",
            "--sidebar-primary-foreground": "60 56% 91%",
            "--sidebar-accent": "60 40% 83%",
            "--sidebar-accent-foreground": "240 100% 25%",
            "--sidebar-border": "240 30% 80%",
            "--sidebar-ring": "240 100% 25%"
        },
        "dark": {
            "--font-sans": "'Roboto', sans-serif",
            "--font-mono": "source-code-pro, Menlo, Monaco, Consolas, 'Courier New', monospace",
            "--background": "240 100% 25%",
            "--foreground": "60 56% 91%",
            "--card": "240 100% 20%",
            "--card-foreground": "60 56% 91%",
            "--popover": "240 100% 20%",
            "--popover-foreground": "60 56% 91%",
            "--primary": "60 56% 91%",
            "--primary-foreground": "240 100% 25%",
            "--secondary": "240 60% 35%",
            "--secondary-foreground": "60 56% 91%",
            "--muted": "240 100% 25%",
            "--muted-foreground": "60 30% 75%",
            "--accent": "240 60% 30%",
            "--accent-foreground": "60 56% 91%",
            "--destructive": "0 62.8% 30.6%",
            "--destructive-foreground": "60 56% 91%",
            "--border": "60 30% 40%",
            "--input": "60 30% 40%",
            "--ring": "60 56% 91%",
            "--radius": "0.75rem",
            "--sidebar-background": "240 100% 18%",
            "--sidebar-foreground": "60 56% 91%",
            "--sidebar-primary": "60 56% 91%",
            "--sidebar-primary-foreground": "240 100% 25%",
            "--sidebar-accent": "240 60% 22%",
            "--sidebar-accent-foreground": "60 56% 91%",
            "--sidebar-border": "60 20% 35%",
            "--sidebar-ring": "60 56% 91%"
        }
    }
}